{
   "type": "arc",
   "rarity": "common",
   "encounters": {
      "wait_for_day_two": "file(encounters/wait_for_day_two.json)",
      "generate daily threat": "file(encounters/generate_daily_threat.json)",
      "generate_random_raiding_party": "file(encounters/generate_random_raiding_party.json)",
      "randomize daily threat": "file(encounters/randomize_daily_threat.json)",
      "wait_to_start_raiding_parties": "file(encounters/wait_to_start_raiding_parties.json)",
      "wait_to_destroy_raiding_party": "file(encounters/wait_to_destroy_raiding_party.json)",
      "destroy_trash_mobs": "file(encounters/destroy_trash_mobs.json)",
      "wait_for_dawn": "file(encounters/wait_for_dawn.json)",
      "destroy_undead": "file(encounters/destroy_undead.json)",
      "goblin thief camp": "file(encounters/goblin_thief_camp.json)",
      "create_thief_camp": "file(encounters/create_thief_camp.json)",
      "spawn thieves": "file(encounters/spawn_thieves.json)",
      "lone thief raid": "file(encounters/lone_thief_raid.json)",
      "goblin night ninjas": "file(encounters/goblin_night_ninja.json)",
      "spawn night ninjas": "file(encounters/spawn_night_ninjas.json)",
      "goblin thieves": "file(encounters/goblin_thieves.json)",
      "wait_to_destroy_raider_raid": "file(encounters/wait_to_destroy_raider_raid.json)",
      "wait_to_destroy_thief_raid": "file(encounters/wait_to_destroy_thief_raid.json)",
      "destroy_raider_raid": "file(encounters/destroy_raider_raid.json)",
      "destroy_thief_raid": "file(encounters/destroy_thief_raid.json)",
      "goblin thug": "file(encounters/goblin_thug.json)",
      "wait for campfire destruction": "file(encounters/wait_for_campfire_destruction.json)",
      "destroy_thief_stockpiles": "file(encounters/destroy_thief_stockpiles.json)",
      "randomize_advanced_threats": "file(encounters/randomize_advanced_threats.json)",
      "goblin raider camp": "file(encounters/goblin_raider_camp.json)",
      "create_raider_camp": "file(encounters/create_raider_camp.json)",
      "spawn raiders": "file(encounters/spawn_raiders.json)",
      "mauraders raid": "file(encounters/mauraders_raid.json)",
      "goblin wolf raid": "file(encounters/goblin_wolf_raid.json)",
      "thief with friends": "file(encounters/thief_with_friends.json)",
      "wait for raider campfire destruction": "file(encounters/wait_for_raider_campfire_destruction.json)",
      "destroy_raider_stockpiles": "file(encounters/destroy_raider_stockpiles.json)",
      "create_zombie_chest_camp": "file(encounters/create_zombie_chest_camp.json)",
      "zombie_chest_camp": "file(encounters/zombie_chest_camp.json)",
      "wait_for_giant_zombie_destruction": "file(encounters/wait_for_giant_zombie_destruction.json)",
      "zombie_chest_camp_destroyed": "file(encounters/zombie_chest_camp_destroyed.json)",
      "wandering_golem": "file(encounters/wandering_golem.json)",
      "golem_raid": "file(encounters/golem_raid.json)",
      "wait_for_three_days": "file(encounters/wait_for_three_days.json)",
      "wait_for_golem_killed": "file(encounters/wait_for_golem_killed.json)",
      "spawn_stonelings": "file(encounters/spawn_stonelings.json)",
      "destroy_golem": "file(encounters/destroy_golem.json)",
      "pack_of_wolves": "file(encounters/pack_of_wolves.json)",
      "wolf_pack_raid": "file(encounters/wolf_pack_raid.json)",
      "wait_for_all_wolves_killed": "file(encounters/wait_for_all_wolves_killed.json)",
      "wolf_pack_killed": "file(encounters/wolf_pack_killed.json)",
      "necromancer_crypt": "file(encounters/necromancer_crypt.json)",
      "create_necromancer_crypt": "file(encounters/create_necromancer_crypt.json)",
      "spawn_necromancer_undead": "file(encounters/spawn_necromancer_undead.json)",
      "wait_for_crypt_attacked": "file(encounters/wait_for_crypt_attacked.json)",
      "wait_to_spawn_nightly_undead": "file(encounters/wait_to_spawn_nightly_undead.json)",
      "generate_nightly_undead": "file(encounters/generate_nightly_undead.json)",
      "spawn_nightly_undead": "file(encounters/spawn_nightly_undead.json)",
      "wait_for_crypt_destroyed": "file(encounters/wait_for_crypt_destroyed.json)",
      "necromancer_crypt_destroyed": "file(encounters/necromancer_crypt_destroyed.json)",
      "alligator_raid_2": "file(encounters/trash_mobs/alligator_raid_2.json)",
      "entling_raid_2": "file(encounters/trash_mobs/entling_raid_2.json)",
      "undead_raid_2": "file(encounters/trash_mobs/undead_raid_2.json)",
      "little_stone_golem_raid_2": "file(encounters/trash_mobs/little_stone_golem_raid_2.json)",
      "wolf_raid_1": "file(encounters/trash_mobs/wolf_raid_1.json)",
      "giant_stoneling_raid_3": "file(encounters/trash_mobs/giant_stoneling_raid_3.json)",
      "golem_family_raid_4": "file(encounters/trash_mobs/golem_family_raid_4.json)",
      "alligator_entling_raid_5": "file(encounters/trash_mobs/alligator_entling_raid_5.json)",
      "giant_wolf_raid_4": "file(encounters/trash_mobs/giant_wolf_raid_4.json)",
      "undead_raid_4": "file(encounters/trash_mobs/undead_raid_4.json)",
      "giant_alligator_raid_6": "file(encounters/trash_mobs/giant_alligator_raid_6.json)",
      "entling_raid_7": "file(encounters/trash_mobs/entling_raid_7.json)",
      "zombie_raid_6": "file(encounters/trash_mobs/zombie_raid_6.json)",
      "golem_family_raid_7": "file(encounters/trash_mobs/golem_family_raid_7.json)",
      "undead_raid_7": "file(encounters/trash_mobs/undead_raid_7.json)",
      "crypt_loot_chest": "file(encounters/crypt_loot_chest.json)",
      "kobold_archer_raid_7": "file(encounters/trash_mobs/kobold_archer_raid_7.json)",
      "ogre_doorbreaker_raid_7": "file(encounters/trash_mobs/ogre_doorbreaker_raid_7.json)",
      "kobold_archer_raid_9": "file(encounters/trash_mobs/kobold_archer_raid_9.json)",
      "kobold_archer_raid_11": "file(encounters/trash_mobs/kobold_archer_raid_11.json)",
      "kobold_archer_raid_13": "file(encounters/trash_mobs/kobold_archer_raid_13.json)",
      "kobold_archer_raid_15": "file(encounters/trash_mobs/kobold_archer_raid_15.json)",
      "ogre_tank_raid_9": "file(encounters/trash_mobs/ogre_tank_raid_9.json)",
      "orc_kobold_raid_9": "file(encounters/trash_mobs/orc_kobold_raid_9.json)",
      "orc_cleric_raid_11": "file(encounters/trash_mobs/orc_cleric_raid_11.json)",
      "orc_wolf_raid_13": "file(encounters/trash_mobs/orc_wolf_raid_13.json)",
      "orc_footman_raid_15": "file(encounters/trash_mobs/orc_footman_raid_15.json)",
      "very_easy_raids": "file(encounters/trash_mobs/raid_difficulty/very_easy_raids.json)",
      "easy_raids": "file(encounters/trash_mobs/raid_difficulty/easy_raids.json)",
      "medium_raids": "file(encounters/trash_mobs/raid_difficulty/medium_raids.json)",
      "hard_raids": "file(encounters/trash_mobs/raid_difficulty/hard_raids.json)",
      "insane_raids": "file(encounters/trash_mobs/raid_difficulty/insane_raids.json)",
      "epic_1_raids": "file(encounters/trash_mobs/raid_difficulty/epic_1_raids.json)",
      "epic_2_raids": "file(encounters/trash_mobs/raid_difficulty/epic_2_raids.json)",
      "epic_3_raids": "file(encounters/trash_mobs/raid_difficulty/epic_3_raids.json)",
      "epic_4_raids": "file(encounters/trash_mobs/raid_difficulty/epic_4_raids.json)",
      "kobold_scout_camp": "file(encounters/kobold_scout_camp.json)",
      "wait_for_kobold_scouts_killed": "file(encounters/wait_for_kobold_scouts_killed.json)",
      "kobold_scouts_killed": "file(encounters/kobold_scouts_killed.json)",
      "create_kobold_scout_camp": "file(encounters/create_kobold_scout_camp.json)",
      "pack_of_alligators": "file(encounters/pack_of_alligators.json)",
      "wait_for_alligator_pack_killed": "file(encounters/wait_for_alligator_pack_killed.json)",
      "alligator_pack_killed": "file(encounters/alligator_pack_killed.json)"
   }
}